README.md
setup.cfg
setup.py
opentree/__init__.py
opentree/node_reference.py
opentree/object_conversion.py
opentree/ot_command_line_tool.py
opentree/ot_object.py
opentree/ot_ws_wrapper.py
opentree/taxonomy_helpers.py
opentree/util.py
opentree/ws_wrapper.py
opentree.egg-info/PKG-INFO
opentree.egg-info/SOURCES.txt
opentree.egg-info/dependency_links.txt
opentree.egg-info/entry_points.txt
opentree.egg-info/requires.txt
opentree.egg-info/top_level.txt
opentree.egg-info/zip-safe
opentree/test/__init__.py
opentree/test/test_chronosynth_deps.py
opentree/test/test_cli.py
opentree/test/test_induced_synth.py
opentree/test/test_ot_methods.py
opentree/test/test_physcraper_deps.py
opentree/test/test_taxonomy_helpers.py
opentree/test/test_util.py