Metadata-Version: 1.1
Name: opentree
Version: 1.0.1
Summary: Library for interacting with Open Tree of Life resources
Home-page: https://github.com/OpenTreeOfLife/python-opentree
Author: Emily Jane B. McTavish and Mark T. Holder
Author-email: UNKNOWN
License: BSD
Download-URL: https://github.com/OpenTreeOfLife/python-opentree/archive/v_0.0.3.tar.gz
Platform: UNKNOWN
Classifier: Development Status :: 4 - Beta
Classifier: Intended Audience :: Science/Research
Classifier: Intended Audience :: Developers
Classifier: Natural Language :: English
Classifier: License :: OSI Approved :: BSD License
Classifier: Operating System :: OS Independent
Classifier: Programming Language :: Python :: 2.7
Classifier: Programming Language :: Python :: 3.4
Classifier: Programming Language :: Python :: 3.3
Classifier: Topic :: Scientific/Engineering :: Bio-Informatics
